setup.py
requests/__init__.py
requests/__version__.py
requests/_internal_utils.py
requests/adapters.py
requests/api.py
requests/auth.py
requests/certs.py
requests/compat.py
requests/cookies.py
requests/exceptions.py
requests/help.py
requests/hooks.py
requests/models.py
requests/packages.py
requests/sessions.py
requests/status_codes.py
requests/structures.py
requests/utils.py
requests_upgrade.egg-info/PKG-INFO
requests_upgrade.egg-info/SOURCES.txt
requests_upgrade.egg-info/dependency_links.txt
requests_upgrade.egg-info/requires.txt
requests_upgrade.egg-info/top_level.txt