Metadata-Version: 2.1
Name: requests-upgrade
Version: 0.0.1
Summary: requests-upgrade
Author: requests-upgrade
